gc_sdk/__init__.py
gc_sdk/functions.py
gc_sdk/main.py
gc_sdk/methods.py
gc_sdk/tests/__init__.py
gc_sdk/tests/functions.py
gc_sdk/tests/main_test.py
gc_sdk/tests/randim.py
gc_sdk/tests/settings_test.py
gcore_interface_sdk-0.190.dist-info/METADATA
gcore_interface_sdk-0.190.dist-info/WHEEL
gcore_interface_sdk-0.190.dist-info/top_level.txt
gcore_interface_sdk-0.190.dist-info/RECORD
