Metadata-Version: 2.1
Name: gcore-interface-sdk
Version: 0.190
Summary: UNKNOWN
Home-page: UNKNOWN
Author: PunchyArchy
Author-email: ksmdrmvscthny@gmail.com
License: UNKNOWN
Platform: UNKNOWN
Requires-Dist: witapi
